[
    {
    "id": 1,
    "name": "Jesus Martin",
    "gender": "diverse",
    "email": "paullopez@example.org",
    "telephone": "1786197448"
    },
    {
    "id": 2,
    "name": "Lindsay Peterson",
    "gender": "female",
    "email": "ymcguire@example.net",
    "telephone": "1885149900"
    },
    {
    "id": 3,
    "name": "Sean Holmes",
    "gender": "male",
    "email": "langjames@example.com",
    "telephone": "3177394061"
    },
    {
    "id": 4,
    "name": "Katherine Wood",
    "gender": "male",
    "email": "stevenmoreno@example.net",
    "telephone": "8211666786"
    },
    {
    "id": 5,
    "name": "Joseph Johnson",
    "gender": "male",
    "email": "fevans@example.org",
    "telephone": "8275704976"
    },
    {
    "id": 6,
    "name": "Pamela Newman",
    "gender": "diverse",
    "email": "ostanley@example.org",
    "telephone": "4462846958"
    },
    {
    "id": 7,
    "name": "Anthony Webb",
    "gender": "male",
    "email": "hoffmanchristopher@example.com",
    "telephone": "8063879300"
    },
    {
    "id": 8,
    "name": "Courtney Perez",
    "gender": "female",
    "email": "howardmichele@example.org",
    "telephone": "4048106532"
    },
    {
    "id": 9,
    "name": "Chad Bradley",
    "gender": "female",
    "email": "lopezcharles@example.com",
    "telephone": "0598475021"
    },
    {
    "id": 10,
    "name": "Danielle Weaver",
    "gender": "male",
    "email": "jacksonvalerie@example.com",
    "telephone": "0418689217"
    },
    {
    "id": 11,
    "name": "David Anderson",
    "gender": "male",
    "email": "phillipsdouglas@example.org",
    "telephone": "0163852516"
    },
    {
    "id": 12,
    "name": "Rachel Martinez",
    "gender": "male",
    "email": "ybenjamin@example.net",
    "telephone": "4843255220"
    },
    {
    "id": 13,
    "name": "Christopher Kelly",
    "gender": "female",
    "email": "adam43@example.net",
    "telephone": "5308149006"
    },
    {
    "id": 14,
    "name": "Dr. Alex Brown MD",
    "gender": "diverse",
    "email": "dianahumphrey@example.com",
    "telephone": "4812533874"
    },
    {
    "id": 15,
    "name": "Patrick Burke",
    "gender": "female",
    "email": "jamiephillips@example.net",
    "telephone": "9812853901"
    },
    {
    "id": 16,
    "name": "James Ibarra",
    "gender": "male",
    "email": "slin@example.org",
    "telephone": "6068135266"
    },
    {
    "id": 17,
    "name": "Anthony Willis",
    "gender": "diverse",
    "email": "nicolerodriguez@example.com",
    "telephone": "8136802516"
    },
    {
    "id": 18,
    "name": "Brandon Lane",
    "gender": "diverse",
    "email": "cfrancis@example.com",
    "telephone": "8296549547"
    },
    {
    "id": 19,
    "name": "Heather Poole",
    "gender": "female",
    "email": "iwilliams@example.com",
    "telephone": "3396689647"
    },
    {
    "id": 20,
    "name": "Joshua Parrish",
    "gender": "female",
    "email": "onealmartin@example.com",
    "telephone": "5100939148"
    },
    {
    "id": 21,
    "name": "Vincent Johnson",
    "gender": "male",
    "email": "daniel76@example.com",
    "telephone": "6521845389"
    },
    {
    "id": 22,
    "name": "Melissa Hampton",
    "gender": "male",
    "email": "fmccoy@example.org",
    "telephone": "5570216694"
    },
    {
    "id": 23,
    "name": "David Reilly",
    "gender": "female",
    "email": "william20@example.com",
    "telephone": "9618056666"
    },
    {
    "id": 24,
    "name": "Joseph Fowler",
    "gender": "diverse",
    "email": "jacob17@example.com",
    "telephone": "9169367236"
    },
    {
    "id": 25,
    "name": "Timothy Powell",
    "gender": "diverse",
    "email": "kelly83@example.com",
    "telephone": "1681018904"
    },
    {
    "id": 26,
    "name": "Gail Clark",
    "gender": "diverse",
    "email": "singhjaime@example.net",
    "telephone": "2390470121"
    },
    {
    "id": 27,
    "name": "Phillip Bell",
    "gender": "female",
    "email": "vyork@example.net",
    "telephone": "3960680350"
    },
    {
    "id": 28,
    "name": "Elizabeth Gilbert",
    "gender": "male",
    "email": "bbishop@example.org",
    "telephone": "6422592232"
    },
    {
    "id": 29,
    "name": "Brandon Price",
    "gender": "diverse",
    "email": "roneal@example.net",
    "telephone": "3347429574"
    },
    {
    "id": 30,
    "name": "Amy Wiley",
    "gender": "diverse",
    "email": "gbates@example.org",
    "telephone": "5984009415"
    },
    {
    "id": 31,
    "name": "Megan Wilson MD",
    "gender": "female",
    "email": "caldwelljames@example.org",
    "telephone": "8588929456"
    },
    {
    "id": 32,
    "name": "Jeremy Dixon",
    "gender": "female",
    "email": "kelly97@example.net",
    "telephone": "4999774188"
    },
    {
    "id": 33,
    "name": "Nancy Navarro",
    "gender": "female",
    "email": "hernandezdaniel@example.com",
    "telephone": "6107079797"
    },
    {
    "id": 34,
    "name": "Steven Sullivan",
    "gender": "male",
    "email": "cgonzalez@example.com",
    "telephone": "4170706263"
    },
    {
    "id": 35,
    "name": "Dana Parker",
    "gender": "diverse",
    "email": "katiebrown@example.org",
    "telephone": "4329504688"
    },
    {
    "id": 36,
    "name": "Mark Richardson",
    "gender": "diverse",
    "email": "cherylrivas@example.com",
    "telephone": "7699384870"
    },
    {
    "id": 37,
    "name": "Michael Shepherd",
    "gender": "female",
    "email": "floresaaron@example.org",
    "telephone": "8152032906"
    },
    {
    "id": 38,
    "name": "Randy Cowan",
    "gender": "female",
    "email": "qmunoz@example.net",
    "telephone": "6840279656"
    },
    {
    "id": 39,
    "name": "Laura Copeland",
    "gender": "female",
    "email": "smithjose@example.net",
    "telephone": "7763157102"
    },
    {
    "id": 40,
    "name": "Thomas Rogers",
    "gender": "female",
    "email": "joshuamckee@example.com",
    "telephone": "4754674497"
    },
    {
    "id": 41,
    "name": "Chad Lane",
    "gender": "diverse",
    "email": "vroberts@example.org",
    "telephone": "3452922467"
    },
    {
    "id": 42,
    "name": "Joshua Ward",
    "gender": "female",
    "email": "henry89@example.org",
    "telephone": "4315632145"
    },
    {
    "id": 43,
    "name": "Mark Mullins",
    "gender": "male",
    "email": "jessica37@example.com",
    "telephone": "8031770688"
    },
    {
    "id": 44,
    "name": "Luis Gregory",
    "gender": "male",
    "email": "jay81@example.net",
    "telephone": "4887009282"
    },
    {
    "id": 45,
    "name": "Elizabeth Martinez",
    "gender": "diverse",
    "email": "gilesheather@example.org",
    "telephone": "0380776071"
    },
    {
    "id": 46,
    "name": "Arthur Mccullough",
    "gender": "diverse",
    "email": "ccollins@example.net",
    "telephone": "0862210966"
    },
    {
    "id": 47,
    "name": "Michael Cox",
    "gender": "female",
    "email": "nicole64@example.com",
    "telephone": "2837088763"
    },
    {
    "id": 48,
    "name": "Alice Smith",
    "gender": "female",
    "email": "michael84@example.net",
    "telephone": "8515774035"
    },
    {
    "id": 49,
    "name": "Kimberly Mendoza",
    "gender": "male",
    "email": "davidsilva@example.net",
    "telephone": "4162362792"
    },
    {
    "id": 50,
    "name": "Samantha Davis",
    "gender": "female",
    "email": "tbrock@example.com",
    "telephone": "4091606309"
    },
    {
    "id": 51,
    "name": "Jeffrey Moore",
    "gender": "male",
    "email": "jason59@example.org",
    "telephone": "9998116869"
    },
    {
    "id": 52,
    "name": "Amy Knapp",
    "gender": "female",
    "email": "gloria43@example.org",
    "telephone": "2204925901"
    },
    {
    "id": 53,
    "name": "Stacy Collins",
    "gender": "male",
    "email": "fbennett@example.org",
    "telephone": "3609084196"
    },
    {
    "id": 54,
    "name": "Steven Galloway",
    "gender": "diverse",
    "email": "ldaniel@example.org",
    "telephone": "1091656057"
    },
    {
    "id": 55,
    "name": "Tracy Diaz",
    "gender": "diverse",
    "email": "sara94@example.net",
    "telephone": "4215594375"
    },
    {
    "id": 56,
    "name": "Christopher Glenn",
    "gender": "male",
    "email": "bennettamanda@example.net",
    "telephone": "7512379908"
    },
    {
    "id": 57,
    "name": "Angela Estrada",
    "gender": "male",
    "email": "kayla82@example.net",
    "telephone": "7392682886"
    },
    {
    "id": 58,
    "name": "Jonathan Wilson",
    "gender": "diverse",
    "email": "roger35@example.org",
    "telephone": "1243826893"
    },
    {
    "id": 59,
    "name": "Lori Marshall",
    "gender": "male",
    "email": "cburke@example.com",
    "telephone": "2096390373"
    },
    {
    "id": 60,
    "name": "George Rodriguez",
    "gender": "diverse",
    "email": "jacquelinerowe@example.com",
    "telephone": "0734958096"
    },
    {
    "id": 61,
    "name": "Valerie Bass",
    "gender": "female",
    "email": "areese@example.net",
    "telephone": "8153680423"
    },
    {
    "id": 62,
    "name": "Jasmine Walker",
    "gender": "female",
    "email": "blawson@example.net",
    "telephone": "8369447751"
    },
    {
    "id": 63,
    "name": "Melinda Lewis",
    "gender": "male",
    "email": "heathashley@example.net",
    "telephone": "5828244565"
    },
    {
    "id": 64,
    "name": "Holly Fry",
    "gender": "diverse",
    "email": "robert70@example.net",
    "telephone": "3348575992"
    },
    {
    "id": 65,
    "name": "Ryan Hall",
    "gender": "diverse",
    "email": "davismelvin@example.org",
    "telephone": "9520120049"
    },
    {
    "id": 66,
    "name": "Sarah Campbell",
    "gender": "diverse",
    "email": "bterry@example.net",
    "telephone": "6011769648"
    },
    {
    "id": 67,
    "name": "Megan Wright",
    "gender": "male",
    "email": "annettemueller@example.com",
    "telephone": "1708548485"
    },
    {
    "id": 68,
    "name": "Stanley Castillo",
    "gender": "male",
    "email": "tammy37@example.net",
    "telephone": "1236820968"
    },
    {
    "id": 69,
    "name": "Crystal Adkins DDS",
    "gender": "female",
    "email": "qbartlett@example.com",
    "telephone": "2516689811"
    },
    {
    "id": 70,
    "name": "Molly Hughes",
    "gender": "diverse",
    "email": "pbenton@example.net",
    "telephone": "3164262479"
    },
    {
    "id": 71,
    "name": "Cynthia Garza",
    "gender": "male",
    "email": "jacksonsamuel@example.net",
    "telephone": "7369843380"
    },
    {
    "id": 72,
    "name": "Michelle Allen",
    "gender": "male",
    "email": "rodgersrobin@example.net",
    "telephone": "2317643395"
    },
    {
    "id": 73,
    "name": "Samantha Lambert",
    "gender": "female",
    "email": "kellybarnes@example.org",
    "telephone": "9315487251"
    },
    {
    "id": 74,
    "name": "Sarah Mitchell",
    "gender": "female",
    "email": "gmiles@example.net",
    "telephone": "8339055633"
    },
    {
    "id": 75,
    "name": "Tina Stuart",
    "gender": "diverse",
    "email": "drewelliott@example.net",
    "telephone": "4439957132"
    },
    {
    "id": 76,
    "name": "Laura West",
    "gender": "female",
    "email": "qgreen@example.com",
    "telephone": "2223487261"
    },
    {
    "id": 77,
    "name": "Carl Willis",
    "gender": "male",
    "email": "daviserik@example.com",
    "telephone": "0048697197"
    },
    {
    "id": 78,
    "name": "Sophia Rodriguez",
    "gender": "male",
    "email": "owalsh@example.com",
    "telephone": "4420659380"
    },
    {
    "id": 79,
    "name": "Caleb Graves",
    "gender": "diverse",
    "email": "leahhayes@example.org",
    "telephone": "7524098542"
    },
    {
    "id": 80,
    "name": "John Nguyen",
    "gender": "male",
    "email": "clairemccoy@example.net",
    "telephone": "3023601764"
    },
    {
    "id": 81,
    "name": "Ryan Johnson",
    "gender": "male",
    "email": "cody98@example.com",
    "telephone": "7375642827"
    },
    {
    "id": 82,
    "name": "Michael Johnson",
    "gender": "female",
    "email": "christina38@example.com",
    "telephone": "7674246877"
    },
    {
    "id": 83,
    "name": "Ashley Alvarado",
    "gender": "female",
    "email": "jeremy27@example.com",
    "telephone": "8422103639"
    },
    {
    "id": 84,
    "name": "Jessica Morris",
    "gender": "female",
    "email": "bkelly@example.net",
    "telephone": "4187727123"
    },
    {
    "id": 85,
    "name": "Jimmy Moore PhD",
    "gender": "female",
    "email": "lopezpaula@example.net",
    "telephone": "4590501132"
    },
    {
    "id": 86,
    "name": "Jimmy Dennis",
    "gender": "female",
    "email": "murphyclinton@example.net",
    "telephone": "3514562155"
    },
    {
    "id": 87,
    "name": "Andrew Davis",
    "gender": "female",
    "email": "luis47@example.org",
    "telephone": "4923348611"
    },
    {
    "id": 88,
    "name": "Alan Johnson",
    "gender": "diverse",
    "email": "tthomas@example.com",
    "telephone": "3580895037"
    },
    {
    "id": 89,
    "name": "Susan Glover",
    "gender": "male",
    "email": "joe50@example.net",
    "telephone": "4704605003"
    },
    {
    "id": 90,
    "name": "Shane Fletcher",
    "gender": "female",
    "email": "bobbygarcia@example.net",
    "telephone": "0016671320"
    },
    {
    "id": 91,
    "name": "Allen Kane",
    "gender": "female",
    "email": "pmartinez@example.net",
    "telephone": "1803323654"
    },
    {
    "id": 92,
    "name": "Kristy Nelson",
    "gender": "female",
    "email": "jason95@example.org",
    "telephone": "2144975560"
    },
    {
    "id": 93,
    "name": "Colton Nichols",
    "gender": "male",
    "email": "michael10@example.net",
    "telephone": "3141829259"
    },
    {
    "id": 94,
    "name": "Natalie Fuller",
    "gender": "female",
    "email": "dlang@example.com",
    "telephone": "1945044785"
    },
    {
    "id": 95,
    "name": "Tiffany Sanchez",
    "gender": "diverse",
    "email": "whitney89@example.com",
    "telephone": "6308571967"
    },
    {
    "id": 96,
    "name": "Sean Gross",
    "gender": "male",
    "email": "reynoldsmark@example.com",
    "telephone": "9103662726"
    },
    {
    "id": 97,
    "name": "Monica Mcknight",
    "gender": "diverse",
    "email": "wrightjennifer@example.com",
    "telephone": "2240111439"
    },
    {
    "id": 98,
    "name": "Douglas Bishop",
    "gender": "male",
    "email": "reevesjoshua@example.org",
    "telephone": "0826063258"
    },
    {
    "id": 99,
    "name": "Donna Friedman",
    "gender": "male",
    "email": "melissa24@example.org",
    "telephone": "2994024785"
    },
    {
    "id": 100,
    "name": "Cory Wilcox",
    "gender": "female",
    "email": "david49@example.org",
    "telephone": "9170591416"
    }
]